flask_zmq/__init__.py
Flask_ZMQ-0.1.2.dist-info/LICENSE
Flask_ZMQ-0.1.2.dist-info/METADATA
Flask_ZMQ-0.1.2.dist-info/WHEEL
Flask_ZMQ-0.1.2.dist-info/top_level.txt
Flask_ZMQ-0.1.2.dist-info/RECORD
